suada/__init__.py
suada/client.py
suada/types.py
tests/__init__.py
tests/test_client.py
tests/test_validation.py
suada-1.3.0rc1.dist-info/METADATA
suada-1.3.0rc1.dist-info/WHEEL
suada-1.3.0rc1.dist-info/top_level.txt
suada-1.3.0rc1.dist-info/RECORD
